dalsa/ALSA.py
dalsa/__init__.py
dalsa-0.0.8.dist-info/METADATA
dalsa-0.0.8.dist-info/WHEEL
dalsa-0.0.8.dist-info/top_level.txt
dalsa-0.0.8.dist-info/RECORD
